Workbook

Sheet Ringkasan
A1: Ringkasan Pengujian Aplikasi Travel
A2: Semua angka di bawah terhitung otomatis dari sheet 'Test Case' dan 'Daftar Bug'.
A4: Modul / Role | B4: Total | C4: Sudah Dicek | D4: PASS | E4: FAIL | F4: BLOCKED | G4: Progres
A5: Autentikasi | B5: =COUNTIF('Test Case'!$B:$B,$A5) | C5: =COUNTIFS('Test Case'!$B:$B,$A5,'Test Case'!$H:$H,"✔") | D5: =COUNTIFS('Test Case'!$B:$B,$A5,'Test Case'!$I:$I,"PASS") | E5: =COUNTIFS('Test Case'!$B:$B,$A5,'Test Case'!$I:$I,"FAIL") | F5: =COUNTIFS('Test Case'!$B:$B,$A5,'Test Case'!$I:$I,"BLOCKED") | G5: =IF(B5=0,0,C5/B5)
A6: Kontrol akses antar role | B6: =COUNTIF('Test Case'!$B:$B,$A6) | C6: =COUNTIFS('Test Case'!$B:$B,$A6,'Test Case'!$H:$H,"✔") | D6: =COUNTIFS('Test Case'!$B:$B,$A6,'Test Case'!$I:$I,"PASS") | E6: =COUNTIFS('Test Case'!$B:$B,$A6,'Test Case'!$I:$I,"FAIL") | F6: =COUNTIFS('Test Case'!$B:$B,$A6,'Test Case'!$I:$I,"BLOCKED") | G6: =IF(B6=0,0,C6/B6)
A7: Publik / Tamu (tanpa login) | B7: =COUNTIF('Test Case'!$B:$B,$A7) | C7: =COUNTIFS('Test Case'!$B:$B,$A7,'Test Case'!$H:$H,"✔") | D7: =COUNTIFS('Test Case'!$B:$B,$A7,'Test Case'!$I:$I,"PASS") | E7: =COUNTIFS('Test Case'!$B:$B,$A7,'Test Case'!$I:$I,"FAIL") | F7: =COUNTIFS('Test Case'!$B:$B,$A7,'Test Case'!$I:$I,"BLOCKED") | G7: =IF(B7=0,0,C7/B7)
A8: Penumpang (role user) › Dashboard & pencarian | B8: =COUNTIF('Test Case'!$B:$B,$A8) | C8: =COUNTIFS('Test Case'!$B:$B,$A8,'Test Case'!$H:$H,"✔") | D8: =COUNTIFS('Test Case'!$B:$B,$A8,'Test Case'!$I:$I,"PASS") | E8: =COUNTIFS('Test Case'!$B:$B,$A8,'Test Case'!$I:$I,"FAIL") | F8: =COUNTIFS('Test Case'!$B:$B,$A8,'Test Case'!$I:$I,"BLOCKED") | G8: =IF(B8=0,0,C8/B8)
A9: Penumpang (role user) › Booking & pembayaran | B9: =COUNTIF('Test Case'!$B:$B,$A9) | C9: =COUNTIFS('Test Case'!$B:$B,$A9,'Test Case'!$H:$H,"✔") | D9: =COUNTIFS('Test Case'!$B:$B,$A9,'Test Case'!$I:$I,"PASS") | E9: =COUNTIFS('Test Case'!$B:$B,$A9,'Test Case'!$I:$I,"FAIL") | F9: =COUNTIFS('Test Case'!$B:$B,$A9,'Test Case'!$I:$I,"BLOCKED") | G9: =IF(B9=0,0,C9/B9)
A10: Penumpang (role user) › Tiket saya, check-in, refund, ulasan | B10: =COUNTIF('Test Case'!$B:$B,$A10) | C10: =COUNTIFS('Test Case'!$B:$B,$A10,'Test Case'!$H:$H,"✔") | D10: =COUNTIFS('Test Case'!$B:$B,$A10,'Test Case'!$I:$I,"PASS") | E10: =COUNTIFS('Test Case'!$B:$B,$A10,'Test Case'!$I:$I,"FAIL") | F10: =COUNTIFS('Test Case'!$B:$B,$A10,'Test Case'!$I:$I,"BLOCKED") | G10: =IF(B10=0,0,C10/B10)
A11: Penumpang (role user) › Promo, notifikasi, akun | B11: =COUNTIF('Test Case'!$B:$B,$A11) | C11: =COUNTIFS('Test Case'!$B:$B,$A11,'Test Case'!$H:$H,"✔") | D11: =COUNTIFS('Test Case'!$B:$B,$A11,'Test Case'!$I:$I,"PASS") | E11: =COUNTIFS('Test Case'!$B:$B,$A11,'Test Case'!$I:$I,"FAIL") | F11: =COUNTIFS('Test Case'!$B:$B,$A11,'Test Case'!$I:$I,"BLOCKED") | G11: =IF(B11=0,0,C11/B11)
A12: Admin Utama (role admin_utama) › Dashboard | B12: =COUNTIF('Test Case'!$B:$B,$A12) | C12: =COUNTIFS('Test Case'!$B:$B,$A12,'Test Case'!$H:$H,"✔") | D12: =COUNTIFS('Test Case'!$B:$B,$A12,'Test Case'!$I:$I,"PASS") | E12: =COUNTIFS('Test Case'!$B:$B,$A12,'Test Case'!$I:$I,"FAIL") | F12: =COUNTIFS('Test Case'!$B:$B,$A12,'Test Case'!$I:$I,"BLOCKED") | G12: =IF(B12=0,0,C12/B12)
A13: Admin Utama (role admin_utama) › Kelola User (pelanggan) | B13: =COUNTIF('Test Case'!$B:$B,$A13) | C13: =COUNTIFS('Test Case'!$B:$B,$A13,'Test Case'!$H:$H,"✔") | D13: =COUNTIFS('Test Case'!$B:$B,$A13,'Test Case'!$I:$I,"PASS") | E13: =COUNTIFS('Test Case'!$B:$B,$A13,'Test Case'!$I:$I,"FAIL") | F13: =COUNTIFS('Test Case'!$B:$B,$A13,'Test Case'!$I:$I,"BLOCKED") | G13: =IF(B13=0,0,C13/B13)
A14: Admin Utama (role admin_utama) › Kelola Staff | B14: =COUNTIF('Test Case'!$B:$B,$A14) | C14: =COUNTIFS('Test Case'!$B:$B,$A14,'Test Case'!$H:$H,"✔") | D14: =COUNTIFS('Test Case'!$B:$B,$A14,'Test Case'!$I:$I,"PASS") | E14: =COUNTIFS('Test Case'!$B:$B,$A14,'Test Case'!$I:$I,"FAIL") | F14: =COUNTIFS('Test Case'!$B:$B,$A14,'Test Case'!$I:$I,"BLOCKED") | G14: =IF(B14=0,0,C14/B14)
A15: Admin Utama (role admin_utama) › Kelola Driver | B15: =COUNTIF('Test Case'!$B:$B,$A15) | C15: =COUNTIFS('Test Case'!$B:$B,$A15,'Test Case'!$H:$H,"✔") | D15: =COUNTIFS('Test Case'!$B:$B,$A15,'Test Case'!$I:$I,"PASS") | E15: =COUNTIFS('Test Case'!$B:$B,$A15,'Test Case'!$I:$I,"FAIL") | F15: =COUNTIFS('Test Case'!$B:$B,$A15,'Test Case'!$I:$I,"BLOCKED") | G15: =IF(B15=0,0,C15/B15)
A16: Admin Utama (role admin_utama) › Memantau Kendaraan | B16: =COUNTIF('Test Case'!$B:$B,$A16) | C16: =COUNTIFS('Test Case'!$B:$B,$A16,'Test Case'!$H:$H,"✔") | D16: =COUNTIFS('Test Case'!$B:$B,$A16,'Test Case'!$I:$I,"PASS") | E16: =COUNTIFS('Test Case'!$B:$B,$A16,'Test Case'!$I:$I,"FAIL") | F16: =COUNTIFS('Test Case'!$B:$B,$A16,'Test Case'!$I:$I,"BLOCKED") | G16: =IF(B16=0,0,C16/B16)
... A27: Skenario lintas role (end-to-end) | B27: =COUNTIF('Test Case'!$B:$B,$A27) | C27: =COUNTIFS('Test Case'!$B:$B,$A27,'Test Case'!$H:$H,"✔") | D27: =COUNTIFS('Test Case'!$B:$B,$A27,'Test Case'!$I:$I,"PASS") | E27: =COUNTIFS('Test Case'!$B:$B,$A27,'Test Case'!$I:$I,"FAIL") | F27: =COUNTIFS('Test Case'!$B:$B,$A27,'Test Case'!$I:$I,"BLOCKED") | G27: =IF(B27=0,0,C27/B27)
A28: TOTAL | B28: =SUM(B5:B27) | C28: =SUM(C5:C27) | D28: =SUM(D5:D27) | E28: =SUM(E5:E27) | F28: =SUM(F5:F27) | G28: =IF(B28=0,0,C28/B28)
A31: Prioritas Bug | B31: Total | C31: Sudah Dicek | D31: Terbukti | E31: Tidak Terbukti
A32: Kritis | B32: =COUNTIF('Daftar Bug'!$B:$B,$A32&"*") | C32: =COUNTIFS('Daftar Bug'!$B:$B,$A32&"*",'Daftar Bug'!$F:$F,"✔") | D32: =COUNTIFS('Daftar Bug'!$B:$B,$A32&"*",'Daftar Bug'!$G:$G,"Ya") | E32: =COUNTIFS('Daftar Bug'!$B:$B,$A32&"*",'Daftar Bug'!$G:$G,"Tidak")
A33: Tinggi | B33: =COUNTIF('Daftar Bug'!$B:$B,$A33&"*") | C33: =COUNTIFS('Daftar Bug'!$B:$B,$A33&"*",'Daftar Bug'!$F:$F,"✔") | D33: =COUNTIFS('Daftar Bug'!$B:$B,$A33&"*",'Daftar Bug'!$G:$G,"Ya") | E33: =COUNTIFS('Daftar Bug'!$B:$B,$A33&"*",'Daftar Bug'!$G:$G,"Tidak")
A34: Sedang | B34: =COUNTIF('Daftar Bug'!$B:$B,$A34&"*") | C34: =COUNTIFS('Daftar Bug'!$B:$B,$A34&"*",'Daftar Bug'!$F:$F,"✔") | D34: =COUNTIFS('Daftar Bug'!$B:$B,$A34&"*",'Daftar Bug'!$G:$G,"Ya") | E34: =COUNTIFS('Daftar Bug'!$B:$B,$A34&"*",'Daftar Bug'!$G:$G,"Tidak")
A35: Rendah | B35: =COUNTIF('Daftar Bug'!$B:$B,$A35&"*") | C35: =COUNTIFS('Daftar Bug'!$B:$B,$A35&"*",'Daftar Bug'!$F:$F,"✔") | D35: =COUNTIFS('Daftar Bug'!$B:$B,$A35&"*",'Daftar Bug'!$G:$G,"Ya") | E35: =COUNTIFS('Daftar Bug'!$B:$B,$A35&"*",'Daftar Bug'!$G:$G,"Tidak")
A36: TOTAL | B36: =SUM(B32:B35) | C36: =SUM(C32:C35) | D36: =SUM(D32:D35) | E36: =SUM(E32:E35)

Sheet Petunjuk & Akun
A1: Cara Mengisi
A2: Kolom yang diisi | B2: Hanya kolom berlatar kuning: Sudah Dicek, Hasil, Hasil Aktual / Catatan, Tanggal Uji, Penguji (sheet Test Case) serta Sudah Dicek, Terbukti?, Catatan (sheet Daftar Bug).
A3: Sudah Dicek | B3: Pilih ✔ dari dropdown setelah test case dijalankan.
A4: Hasil | B4: PASS = sesuai harapan · FAIL = tidak sesuai · BLOCKED = tidak bisa diuji (mis. data/akun belum siap).
A5: Hasil Aktual / Catatan | B5: Tulis apa yang benar-benar terjadi, terutama jika FAIL (pesan error, URL, screenshot).
A6: Tanggal Uji | B6: Format dd/mm/yyyy, contoh 16/10/2026.
A7: Bug Terkait (merah) | B7: Test case ini mengarah ke bug yang sudah ditemukan lewat review kode; kemungkinan besar hasilnya FAIL.
A8: Terbukti? (Daftar Bug) | B8: Ya = bug benar terjadi saat diuji · Tidak = tidak terjadi.
A9: Reset data sebelum uji | B9: php artisan migrate:fresh --seed lalu npm run build (atau composer run dev)
A12: Akun Uji
A13: Role | B13: Halaman login | C13: Email | D13: Password | E13: Kode akses
A14: Admin Utama (admin_utama) | B14: /login | C14: admin@travel.test | D14: password | E14: ADMIN123
A15: Staff Jakarta (staff) | B15: /login | C15: staff@travel.test | D15: password | E15: STF-2026-TRAVEL
A16: Staff Bandung (staff) | B16: /login | C16: staff.bandung@travel.test | D16: password | E16: STF-BDO-2026
A17: Customer Service (cs) | B17: /login | C17: cs@travel.test | D17: password | E17: CS-2026-TRAVEL
A18: Driver (driver) | B18: /login | C18: driver@travel.test | D18: password | E18: DRV-2026-TRAVEL
A19: Driver lain | B19: /login | C19: driver.bambang@travel.test (dan driver.*@travel.test lainnya) | D19: password | E19: DRV-2026-TRAVEL
A20: Penumpang (user) | B20: /user/login | C20: user@travel.test | D20: password | E20: (tidak ada)
A21: Penumpang lain | B21: /user/login | C21: budi@, dewi@, rizky@, anisa@travel.test | D21: password | E21: (tidak ada)
A23: Data Uji
A24: Data | B24: Nilai
A25: Kode promo checkout | B25: HEMATLIBURAN (25%, maks Rp50.000, min Rp100.000, khusus Bandung–Jakarta), TRAVELHEMAT (Rp20.000, min Rp100.000)
A26: Kode klaim voucher | B26: HEMATLIBURAN, TRAVELHEMAT, KOMPENSASI50, WELCOME2026, SUPERDISCOUNT
A27: NIK valid | B27: 16 digit angka, mis. 3273010198000001
A28: Kanal bayar | B28: bca, mandiri, bni, bri, bsi, seabank, qris, gopay, shopeepay

Sheet Test Case
A1: No | B1: Modul / Role | C1: ID | D1: Skenario | E1: Langkah / Data Uji | F1: Hasil yang Diharapkan | G1: Bug Terkait | H1: Sudah Dicek | I1: Hasil | J1: Hasil Aktual / Catatan | K1: Tanggal Uji | L1: Penguji
A2: 1 | B2: Autentikasi | C2: AUTH-01 | D2: Login admin utama valid | E2: /login, role Admin Utama, admin@travel.test / password / ADMIN123 | F2: Masuk ke /dashboard/admin
A3: 2 | B3: Autentikasi | C3: AUTH-02 | D3: Login staff valid | E3: role Staff, staff@travel.test / password / STF-2026-TRAVEL | F3: Masuk ke /admin/dashboard
A4: 3 | B4: Autentikasi | C4: AUTH-03 | D4: Login CS valid | E4: role CS, cs@travel.test / password / CS-2026-TRAVEL | F4: Masuk ke /customer-service/dashboard
A5: 4 | B5: Autentikasi | C5: AUTH-04 | D5: Login driver valid | E5: role Driver, driver@travel.test / password / DRV-2026-TRAVEL | F5: Masuk ke /driver/dashboard
A6: 5 | B6: Autentikasi | C6: AUTH-05 | D6: Password salah | E6: Password salah123 | F6: Tetap di /login, error "Email atau password salah."
A7: 6 | B7: Autentikasi | C7: AUTH-06 | D7: Role tidak sesuai akun | E7: staff@travel.test tapi pilih role Driver | F7: Error "Role yang dipilih tidak sesuai dengan akun Anda."
A8: 7 | B8: Autentikasi | C8: AUTH-07 | D8: Kode akses salah | E8: Kode akses XXX | F8: Error "Kode akses tidak valid."
A9: 8 | B9: Autentikasi | C9: AUTH-08 | D9: Field kosong | E9: Submit form kosong | F9: Pesan wajib isi untuk email, password, role, kode akses
A10: 9 | B10: Autentikasi | C10: AUTH-09 | D10: Petugas nonaktif login | E10: Nonaktifkan staff (ADM-STF-06), lalu login | F10: Ditolak dengan pesan akun nonaktif (BUG-02) | G10: BUG-02
A11: 10 | B11: Autentikasi | C11: AUTH-10 | D11: Login penumpang valid | E11: /user/login, user@travel.test / password | F11: Masuk ke /user/dashboard
A12: 11 | B12: Autentikasi | C12: AUTH-11 | D12: Petugas login di form penumpang | E12: /user/login dengan admin@travel.test | F12: Ditolak "Email atau password salah."
A13: 12 | B13: Autentikasi | C13: AUTH-12 | D13: Redirect setelah login | E13: Buka /user/login?redirect=<url hasil cari> lalu login | F13: Kembali ke URL hasil pencarian
A14: 13 | B14: Autentikasi | C14: AUTH-13 | D14: Redirect ke domain luar | E14: /user/login?redirect=https://evil.com | F14: Redirect diabaikan, masuk ke /user/dashboard
A15: 14 | B15: Autentikasi | C15: AUTH-14 | D15: Role admin/customer_service | E15: Buat user role admin, coba login | F15: Bisa login atau memang tidak didukung; perlu keputusan (BUG-24) | G15: BUG-24
A16: 15 | B16: Autentikasi | C16: AUTH-15 | D16: Registrasi penumpang | E16: /register: nama, email baru, HP, password 8+ karakter + konfirmasi | F16: Akun role user dibuat dan langsung login
A17: 16 | B17: Autentikasi | C17: AUTH-16 | D17: Penumpang diblokir login | E17: Blokir user (ADM-USR-07), login di /user/login | F17: Ditolak (BUG-02) | G17: BUG-02
A18: 17 | B18: Autentikasi | C18: AUTH-17 | D18: Registrasi email duplikat | E18: Email user@travel.test | F18: Error email sudah dipakai
A19: 18 | B19: Autentikasi | C19: AUTH-18 | D19: Registrasi password pendek / tidak cocok | E19: Password 1234567, atau konfirmasi berbeda | F19: Error validasi min 8 / konfirmasi
A20: 19 | B20: Autentikasi | C20: AUTH-19 | D20: Lupa password | E20: /forgot-password, email terdaftar | F20: Pesan link reset terkirim (cek mail log)
A21: 20 | B21: Autentikasi | C21: AUTH-20 | D21: Lupa password, email tidak terdaftar | E21: email acak | F21: Pesan error dari Laravel
A22: 21 | B22: Autentikasi | C22: AUTH-21 | D22: Reset password | E22: Buka link dari email, isi password baru | F22: Password berubah, bisa login dengan password baru
A23: 22 | B23: Autentikasi | C23: AUTH-22 | D23: Login Google belum dikonfigurasi | E23: GOOGLE_CLIENT_ID kosong, klik "Masuk dengan Google" | F23: Kembali ke /user/login dengan pesan "belum bisa dipakai"
A24: 23 | B24: Autentikasi | C24: AUTH-23 | D24: Login Google akun baru | E24: Google OAuth dengan email baru | F24: Akun role user dibuat, email terverifikasi, masuk dashboard
A25: 24 | B25: Autentikasi | C25: AUTH-24 | D25: Login Google pakai email petugas | E25: Email Google = cs@travel.test | F25: Ditolak: "terdaftar sebagai akun petugas"
A26: 25 | B26: Autentikasi | C26: AUTH-25 | D26: Google meng-klaim booking tamu | E26: Pesan sebagai tamu dengan email X, lalu login Google dengan email X | F26: Booking tamu pindah ke akun
A27: 26 | B27: Autentikasi | C27: AUTH-26 | D27: Logout petugas | E27: Klik Keluar di dashboard petugas | F27: Sesi berakhir, kembali ke /login
A28: 27 | B28: Autentikasi | C28: AUTH-27 | D28: Logout penumpang | E28: Klik Keluar di dashboard penumpang | F28: Kembali ke /user/login
A29: 28 | B29: Autentikasi | C29: AUTH-28 | D29: Halaman login saat sudah login | E29: Login, lalu buka /login atau /register | F29: Diarahkan keluar dari halaman tamu
... A63: 62 | B63: Penumpang (role user) › Booking & pembayaran | C63: USR-BK-08 | D63: Seat map kursi lunas | E63: Buka seat map jadwal yang ada booking lunas | F63: Kursi lunas tampil terisi, tidak bisa dipilih
A64: 63 | B64: Penumpang (role user) › Booking & pembayaran | C64: USR-BK-09 | D64: Kursi penumpang yang sudah check-in | E64: Booking A lunas lalu check-in mandiri (USR-TK-03); akun B buka seat map jadwal yang sama | F64: Kursi A tetap terisi dan tidak bisa dikunci (BUG-05) | G64: BUG-05
A65: 64 | B65: Penumpang (role user) › Booking & pembayaran | C65: USR-BK-10 | D65: Jadwal batal/lewat lewat URL langsung | E65: Admin set jadwal Cancelled, lalu buka /user/booking/pilih-kursi/{id} dan kunci kursi | F65: Ditolak (BUG-20) | G65: BUG-20
A66: 65 | B66: Penumpang (role user) › Booking & pembayaran | C66: USR-BK-11 | D66: Validasi data pemesan | E66: HP abc, email tidak valid, nama kosong | F66: Error validasi; HP harus angka/+/-, min 8
A67: 66 | B67: Penumpang (role user) › Booking & pembayaran | C67: USR-BK-12 | D67: Promo HEMATLIBURAN | E67: Rute Bandung–Jakarta, subtotal ≥ 100.000 | F67: Diskon 25%, maks Rp50.000
A68: 67 | B68: Penumpang (role user) › Booking & pembayaran | C68: USR-BK-13 | D68: HEMATLIBURAN rute lain / di bawah minimum | E68: Rute non Bandung–Jakarta, atau subtotal < 100.000 | F68: Validasi promo menolak dengan pesan yang sesuai
A69: 68 | B69: Penumpang (role user) › Booking & pembayaran | C69: USR-BK-14 | D69: Voucher dompet diterapkan | E69: Klaim KOMPENSASI50, pakai di checkout (subtotal ≥ 50.000), simpan | F69: Total di halaman pembayaran berkurang Rp50.000 (BUG-07) | G69: BUG-07
A70: 69 | B70: Penumpang (role user) › Booking & pembayaran | C70: USR-BK-15 | D70: Voucher sekali pakai | E70: Bayar dengan voucher (USR-BK-14), lalu pakai kode yang sama di booking baru | F70: Ditolak "sudah pernah digunakan" (BUG-07) | G70: BUG-07
A71: 70 | B71: Penumpang (role user) › Booking & pembayaran | C71: USR-BK-16 | D71: Kode promo tidak dikenal | E71: ASAL123 | F71: "Kode voucer … tidak ditemukan"
A72: 71 | B72: Penumpang (role user) › Booking & pembayaran | C72: USR-BK-17 | D72: Ganti metode bayar | E72: Di halaman pembayaran, pindah BCA → QRIS → GoPay | F72: Instruksi bayar berganti sesuai kanal
A73: 72 | B73: Penumpang (role user) › Booking & pembayaran | C73: USR-BK-18 | D73: Simpan ulang data booking lunas | E73: Setelah lunas, kirim ulang POST save-passenger/{id} | F73: Ditolak/redirect ke sukses; status pembayaran tetap lunas (BUG-19) | G73: BUG-19
A74: 73 | B74: Penumpang (role user) › Booking & pembayaran | C74: USR-BK-19 | D74: Simulasi bayar (non-production) | E74: Klik tombol simulasi bayar | F74: Booking confirmed, tiket terbit, email tiket terkirim 1x
A75: 74 | B75: Penumpang (role user) › Booking & pembayaran | C75: USR-BK-20 | D75: Simulasi bayar di production | E75: APP_ENV=production, panggil simulate-payment | F75: 404
A76: 75 | B76: Penumpang (role user) › Booking & pembayaran | C76: USR-BK-21 | D76: Polling status | E76: Buka /user/booking/pembayaran/{id}/status | F76: JSON is_paid sesuai status
A77: 76 | B77: Penumpang (role user) › Booking & pembayaran | C77: USR-BK-22 | D77: Halaman sukses booking belum lunas | E77: Buka /user/booking/sukses/{id} saat pending | F77: Redirect ke halaman pembayaran
A78: 77 | B78: Penumpang (role user) › Tiket saya, check-in, refund, ulasan | C78: USR-TK-01 | D78: Daftar tiket aktif | E78: Buka /tiket/dashboard | F78: Tiket lunas yang akan berangkat tampil dengan QR
A79: 78 | B79: Penumpang (role user) › Tiket saya, check-in, refund, ulasan | C79: USR-TK-02 | D79: Riwayat otomatis | E79: Tiket dengan keberangkatan > 1 jam lalu | F79: Pindah ke tab Riwayat, status completed
A80: 79 | B80: Penumpang (role user) › Tiket saya, check-in, refund, ulasan | C80: USR-TK-03 | D80: Check-in mandiri | E80: Klik check-in pada tiket aktif | F80: Tiket Boarded, semua penumpang boarded
A81: 80 | B81: Penumpang (role user) › Tiket saya, check-in, refund, ulasan | C81: USR-TK-04 | D81: Check-in tiket yang dibatalkan | E81: Batalkan booking (refund), lalu kirim POST /user/tiket/{ticket}/check-in | F81: Ditolak (BUG-08) | G81: BUG-08
A82: 81 | B82: Penumpang (role user) › Tiket saya, check-in, refund, ulasan | C82: USR-TK-05 | D82: Check-in booking belum bayar | E82: Kirim check-in dengan ID booking pending | F82: Ditolak, tidak ada tiket terbit (BUG-08) | G82: BUG-08
A83: 82 | B83: Penumpang (role user) › Tiket saya, check-in, refund, ulasan | C83: USR-TK-06 | D83: Ajukan refund ≥ 1 jam sebelum berangkat | E83: Isi alasan, bank, no rekening, pemilik | F83: Refund 75% (potongan 25%), booking batal, kursi dilepas
A84: 83 | B84: Penumpang (role user) › Tiket saya, check-in, refund, ulasan | C84: USR-TK-07 | D84: Refund < 1 jam sebelum berangkat | E84: Jadwal 30 menit lagi | F84: Ditolak: batas waktu pembatalan berakhir
A85: 84 | B85: Penumpang (role user) › Tiket saya, check-in, refund, ulasan | C85: USR-TK-08 | D85: Refund booking belum bayar / sudah batal | E85: Booking pending atau cancelled | F85: Ditolak
A86: 85 | B86: Penumpang (role user) › Tiket saya, check-in, refund, ulasan | C86: USR-TK-09 | D86: Refund field kosong | E86: Kosongkan bank/rekening | F86: Error validasi
A87: 86 | B87: Penumpang (role user) › Tiket saya, check-in, refund, ulasan | C87: USR-TK-10 | D87: Kirim ulasan | E87: Nilai 1–5 untuk 3 aspek + komentar | F87: Ulasan tersimpan, rata-rata dihitung
A88: 87 | B88: Penumpang (role user) › Tiket saya, check-in, refund, ulasan | C88: USR-TK-11 | D88: Ulasan nilai di luar batas | E88: Nilai 0 atau 6, komentar > 1000 karakter | F88: Error validasi
A89: 88 | B89: Penumpang (role user) › Tiket saya, check-in, refund, ulasan | C89: USR-TK-12 | D89: Ulasan sebelum perjalanan | E89: Kirim ulasan untuk booking pending/akan datang | F89: Ditolak (BUG-23) | G89: BUG-23
A90: 89 | B90: Penumpang (role user) › Promo, notifikasi, akun | C90: USR-PR-01 | D90: Lihat dompet voucher | E90: /promo/dashboard, filter all/active/used/expired | F90: Daftar dan jumlah per status benar
A91: 90 | B91: Penumpang (role user) › Promo, notifikasi, akun | C91: USR-PR-02 | D91: Klaim voucher valid | E91: Kode WELCOME2026 | F91: Voucher masuk dompet, aktif 30 hari
A92: 91 | B92: Penumpang (role user) › Promo, notifikasi, akun | C92: USR-PR-03 | D92: Klaim voucher yang masih aktif | E92: Klaim WELCOME2026 lagi | F92: Ditolak: "sudah ada … masih aktif"
A93: 92 | B93: Penumpang (role user) › Promo, notifikasi, akun | C93: USR-PR-04 | D93: Kode tidak valid | E93: ABCDEF | F93: "tidak valid atau promo sudah berakhir"
A94: 93 | B94: Penumpang (role user) › Promo, notifikasi, akun | C94: USR-PR-05 | D94: Klaim ulang voucher kedaluwarsa/terpakai | E94: Ubah expires_at voucher ke kemarin, klaim lagi | F94: Seharusnya ditolak (BUG-07) | G94: BUG-07
A95: 94 | B95: Penumpang (role user) › Promo, notifikasi, akun | C95: USR-NT-01 | D95: Daftar notifikasi | E95: /notifikasi/dashboard, filter transaksi/pengingat/operasional | F95: Daftar dan jumlah per kategori benar
A96: 95 | B96: Penumpang (role user) › Promo, notifikasi, akun | C96: USR-NT-02 | D96: Buka notifikasi | E96: Klik notifikasi | F96: Ditandai dibaca, diarahkan ke deep link
A97: 96 | B97: Penumpang (role user) › Promo, notifikasi, akun | C97: USR-NT-03 | D97: Tandai semua dibaca | E97: Klik "tandai semua" | F97: Jumlah belum dibaca jadi 0
A98: 97 | B98: Penumpang (role user) › Promo, notifikasi, akun | C98: USR-NT-04 | D98: Hapus notifikasi | E98: Hapus satu notifikasi | F98: Hilang dari daftar
A99: 98 | B99: Penumpang (role user) › Promo, notifikasi, akun | C99: USR-NT-05 | D99: Buka notifikasi milik user lain | E99: /user/notifikasi/{id milik user lain}/open | F99: 404
A100: 99 | B100: Penumpang (role user) › Promo, notifikasi, akun | C100: USR-NT-06 | D100: Simulasi notifikasi | E100: Kirim tipe pending, confirmed, expired, reminder_2h, operational_vehicle, operational_delay | F100: Masing-masing muncul dengan isi sesuai
A101: 100 | B101: Penumpang (role user) › Promo, notifikasi, akun | C101: USR-AK-01 | D101: Ubah profil | E101: Nama, email baru, HP | F101: Tersimpan
A102: 101 | B102: Penumpang (role user) › Promo, notifikasi, akun | C102: USR-AK-02 | D102: Email sudah dipakai | E102: Email budi@travel.test | F102: Error unique
A103: 102 | B103: Penumpang (role user) › Promo, notifikasi, akun | C103: USR-AK-03 | D103: Ganti password | E103: Password lama benar, baru 8+ dan konfirmasi | F103: Berhasil, login dengan password baru
A104: 103 | B104: Penumpang (role user) › Promo, notifikasi, akun | C104: USR-AK-04 | D104: Password lama salah | E104: Password lama salah | F104: "Kata sandi saat ini … salah"
A105: 104 | B105: Penumpang (role user) › Promo, notifikasi, akun | C105: USR-AK-05 | D105: Tambah penumpang tersimpan | E105: Nama + NIK 16 digit | F105: Tersimpan
A106: 105 | B106: Penumpang (role user) › Promo, notifikasi, akun | C106: USR-AK-06 | D106: NIK tidak valid | E106: NIK 15 digit atau ada huruf | F106: Error NIK 16 digit
... A112: 111 | B112: Admin Utama (role admin_utama) › Kelola User (pelanggan) | C112: ADM-USR-02 | D112: Tambah user | E112: Nama, email baru, password 8+ + konfirmasi | F112: User role user aktif dibuat
A113: 112 | B113: Admin Utama (role admin_utama) › Kelola User (pelanggan) | C113: ADM-USR-03 | D113: Tambah user email duplikat / password tidak cocok | F113: Error validasi berbahasa Indonesia
A114: 113 | B114: Admin Utama (role admin_utama) › Kelola User (pelanggan) | C114: ADM-USR-04 | D114: Detail user | E114: Klik user | F114: Profil & riwayat perjalanan tampil
A115: 114 | B115: Admin Utama (role admin_utama) › Kelola User (pelanggan) | C115: ADM-USR-05 | D115: Detail/edit akun petugas lewat URL user | E115: /kelola-user/{id staff} | F115: 404
A116: 115 | B116: Admin Utama (role admin_utama) › Kelola User (pelanggan) | C116: ADM-USR-06 | D116: Edit user | E116: Ubah nama/HP | F116: Tersimpan
A117: 116 | B117: Admin Utama (role admin_utama) › Kelola User (pelanggan) | C117: ADM-USR-07 | D117: Blokir user | E117: Toggle status lalu user mencoba login | F117: Status inactive dan login ditolak (BUG-02) | G117: BUG-02
A118: 117 | B118: Admin Utama (role admin_utama) › Kelola User (pelanggan) | C118: ADM-USR-08 | D118: Reset password user | E118: Password baru + konfirmasi | F118: User bisa login dengan password baru
A119: 118 | B119: Admin Utama (role admin_utama) › Kelola User (pelanggan) | C119: ADM-USR-09 | D119: Hapus user yang punya transaksi | E119: Hapus user dengan booking lunas, lalu buka laporan | F119: Seharusnya dicegah atau data transaksi tetap ada (BUG-21) | G119: BUG-21
A120: 119 | B120: Admin Utama (role admin_utama) › Kelola Staff | C120: ADM-STF-01 | D120: Tambah staff | E120: Nama, email, HP, cabang, password + konfirmasi, hak akses | F120: Staff aktif dibuat
A121: 120 | B121: Admin Utama (role admin_utama) › Kelola Staff | C121: ADM-STF-02 | D121: Staff baru login (dengan kode akses) | E121: Buat staff dengan kode akses STF-NEW-01, login di /login | F121: Login berhasil. Saat ini: error 500 (BUG-03) | G121: BUG-03
A122: 121 | B122: Admin Utama (role admin_utama) › Kelola Staff | C122: ADM-STF-03 | D122: Staff baru tanpa kode akses | E122: Buat staff tanpa kode akses, login | F122: Ada cara login / kode digenerate. Saat ini tidak bisa login (BUG-03) | G122: BUG-03
A123: 122 | B123: Admin Utama (role admin_utama) › Kelola Staff | C123: ADM-STF-04 | D123: Validasi tambah staff | E123: Kosongkan cabang/HP, email duplikat | F123: Error validasi
A124: 123 | B124: Admin Utama (role admin_utama) › Kelola Staff | C124: ADM-STF-05 | D124: Edit staff & hak akses | E124: Ubah cabang, hapus hak checkin_ticket | F124: Tersimpan
A125: 124 | B125: Admin Utama (role admin_utama) › Kelola Staff | C125: ADM-STF-06 | D125: Nonaktifkan staff | E125: Toggle status lalu staff login | F125: Login ditolak (BUG-02) | G125: BUG-02
A126: 125 | B126: Admin Utama (role admin_utama) › Kelola Staff | C126: ADM-STF-07 | D126: Reset password staff | F126: Staff login dengan password baru
A127: 126 | B127: Admin Utama (role admin_utama) › Kelola Staff | C127: ADM-STF-08 | D127: Hapus staff | E127: Hapus staff lain | F127: Terhapus
A128: 127 | B128: Admin Utama (role admin_utama) › Kelola Staff | C128: ADM-STF-09 | D128: URL staff untuk akun non-staff | E128: /kelola-staff/{id user} | F128: 404
A129: 128 | B129: Admin Utama (role admin_utama) › Kelola Driver | C129: ADM-DRV-01 | D129: Tambah driver | E129: Data lengkap + SIM unik + foto ≤ 2MB | F129: Driver & akun user role driver dibuat
A130: 129 | B130: Admin Utama (role admin_utama) › Kelola Driver | C130: ADM-DRV-02 | D130: Driver baru login | E130: Login driver baru di /login | F130: Bisa login. Saat ini tidak punya kode akses (BUG-04) | G130: BUG-04
A131: 130 | B131: Admin Utama (role admin_utama) › Kelola Driver | C131: ADM-DRV-03 | D131: SIM duplikat / foto > 2MB / bukan gambar | F131: Error validasi
A132: 131 | B132: Admin Utama (role admin_utama) › Kelola Driver | C132: ADM-DRV-04 | D132: Edit driver | E132: Ubah SIM, status | F132: Tersimpan
A133: 132 | B133: Admin Utama (role admin_utama) › Kelola Driver | C133: ADM-DRV-05 | D133: Ubah status cepat | E133: standby → on_duty → on_leave | F133: Tersimpan
A134: 133 | B134: Admin Utama (role admin_utama) › Kelola Driver | C134: ADM-DRV-06 | D134: Hapus driver yang punya jadwal mendatang | F134: Seharusnya dicegah. Saat ini jadwal kehilangan sopir tanpa peringatan
A135: 134 | B135: Admin Utama (role admin_utama) › Memantau Kendaraan | C135: ADM-VH-01 | D135: Daftar & peringatan KIR/STNK | E135: Kendaraan dengan KIR/STNK hampir habis | F135: Peringatan legalitas tampil
A136: 135 | B136: Admin Utama (role admin_utama) › Memantau Kendaraan | C136: ADM-VH-02 | D136: Tambah kendaraan | E136: Plat unik, kapasitas 4–60, tahun 1990–tahun depan | F136: Dibuat, kursi otomatis dibuat
A137: 136 | B137: Admin Utama (role admin_utama) › Memantau Kendaraan | C137: ADM-VH-03 | D137: Validasi kendaraan | E137: Plat duplikat, kapasitas 3 atau 61, tahun 1989 | F137: Error validasi
A138: 137 | B138: Admin Utama (role admin_utama) › Memantau Kendaraan | C138: ADM-VH-04 | D138: Edit kendaraan | E138: Ubah fasilitas & foto | F138: Tersimpan
...

Sheet Daftar Bug
A1: ID | B1: Prioritas | C1: Masalah | D1: Lokasi Kode | E1: Test Case Terkait | F1: Sudah Dicek | G1: Terbukti? | H1: Catatan
A2: BUG-01 | B2: Kritis | C2: Webhook pembayaran menerima request tanpa signature_key (verifikasi hanya jalan kalau field itu dikirim). Jika transaction_status kosong, nilai default-nya settlement. Siapa pun yang tahu order_id bisa menandai pesanan lunas dengan POST /api/payment/webhook {"order_id":"..."}. | D2: UserDashboardController@paymentWebhook | E2: PAY-05, PAY-06
A3: BUG-02 | B3: Kritis | C3: Akun yang dinonaktifkan/diblokir (status = inactive) tetap bisa login. Status tidak dicek di login penumpang, login petugas, maupun login Google. | D3: Auth/LoginController, Auth/UserLoginController, Auth/GoogleLoginController | E3: AUTH-09, AUTH-16, ADM-USR-07, ADM-STF-06
A4: BUG-03 | B4: Kritis (terkonfirmasi) | C4: Kode akses staf dari form Kelola Staff disimpan plaintext, padahal login memakai Hash::check. Login staf baru itu menghasilkan error 500 (RuntimeException: This password does not use the Bcrypt algorithm). Staf yang dibuat tanpa kode akses tidak bisa login sama sekali. | D4: AdminDashboardController@storeStaff/updateStaff | E4: ADM-STF-02, ADM-STF-03
A5: BUG-04 | B5: Kritis | C5: Driver yang dibuat lewat Kelola Driver tidak diberi kode akses, jadi tidak bisa login. | D5: AdminDashboardController@storeDriver | E5: ADM-DRV-02
A6: BUG-05 | B6: Kritis | C6: Seat map dan proses kunci kursi hanya menganggap status paid/confirmed/success/lunas sebagai terisi. Kursi milik booking checked_in (penumpang yang sudah check-in mandiri) tampil kosong dan bisa dipesan orang lain sehingga terjadi double booking. Di SQLite, booking manual berstatus Paid/Pending (huruf kapital) juga lolos dari pengecekan. | D6: UserDashboardController@lockSeats, buildSeatOccupancyMap | E6: USR-BK-09, X-03
A7: BUG-06 | B7: Kritis | C7: Endpoint aksi driver tidak mengecek kepemilikan jadwal. Driver A bisa mengubah status trip, GPS, laporan, dan SOS jadwal driver lain, serta check-in penumpang mana pun. Dengan mark_paid=1, driver bisa membuat booking belum bayar menjadi confirmed. | D7: DriverDashboardController@updateTripStatus/updateGps/updateCheckin/reportIncident/triggerSos | E7: DRV-12, DRV-13
A8: BUG-07 | B8: Tinggi | C8: Voucher dompet (KOMPENSASI50, WELCOME2026, SUPERDISCOUNT) lolos validasi promo tapi diskonnya tidak diterapkan saat data disimpan. HEMATLIBURAN diterapkan tanpa cek rute. Voucher tidak pernah ditandai terpakai sehingga bisa dipakai berulang, dan voucher kedaluwarsa bisa diklaim ulang tanpa batas. | D8: savePassengerData, claimVoucher | E8: USR-BK-14, USR-BK-15, USR-PR-05
A9: BUG-08 | B9: Tinggi | C9: Check-in mandiri penumpang tidak mengecek status. Booking pending (belum bayar) atau tiket cancelled tetap bisa di-check-in, dan booking pending bisa langsung dibuatkan tiket. | D9: checkInTicket | E9: USR-TK-04, USR-TK-05
A10: BUG-09 | B10: Tinggi | C10: Refund dari penumpang berstatus Diajukan, tapi admin dan CS hanya menghitung Menunggu/Pending. Akibatnya: (a) counter refund pending tidak bertambah, (b) admin bisa membuat refund ganda untuk booking yang sama, (c) kalau admin menolak refund penumpang, booking tetap batal dan kursi sudah dilepas, padahal pesan sistem bilang "tiket tetap aktif". | D10: submitRefund, refundIndex, storeRefund, rejectRefund, CustomerServiceDashboardController@index | E10: ADM-RF-03, ADM-RF-07, CS-03
A11: BUG-10 | B11: Tinggi | C11: Approve pembayaran manual tidak mengecek status booking atau bentrok kursi, sehingga booking yang sudah batal/kedaluwarsa bisa hidup lagi walau kursinya sudah dipakai orang lain. Reject pada pembayaran yang sudah lunas ikut membatalkan booking lunas. | D11: verifyPayment | E11: ADM-PAY-05, ADM-PAY-06
A12: BUG-11 | B12: Tinggi | C12: Sinkron gateway dengan status expire mengubah booking menjadi Expired, tapi perhitungan sisa kursi hanya mengecualikan cancelled, jadi kursi tidak pernah dilepas. | D12: syncGatewayStatus, Schedule::recalculateAvailableSeats | E12: ADM-PAY-09
A13: BUG-12 | B13: Tinggi | C13: Menghapus kendaraan yang punya jadwal lampau atau selesai menghasilkan error 500 (foreign key restrictOnDelete di schedules.vehicle_id dan booking_passengers.seat_id). | D13: destroyVehicle | E13: ADM-VH-07
... A25: BUG-24 | B25: Rendah | C25: UserSeeder (role admin) tidak dipanggil DatabaseSeeder, dan role admin/customer_service diizinkan route tapi tidak bisa dipilih di form login. | D25: LoginController, seeder | E25: AUTH-14
